builtapi/__init__.py
builtapi/api/__init__.py
builtapi/api/main.py
builtapi/core/__init__.py
builtapi/core/convert/__init__.py
builtapi/core/convert/entities.py
builtapi/core/convert/members.py
builtapi/core/convert/records.py
builtapi/core/convert/users.py
builtapi/core/convert/views.py
builtapi/core/convert/workspaces.py
builtapi/core/modules/__init__.py
builtapi/core/modules/common.py
builtapi/core/modules/entities.py
builtapi/core/modules/members.py
builtapi/core/modules/records.py
builtapi/core/modules/users.py
builtapi/core/modules/views.py
builtapi/core/modules/workspaces.py
builtapi/core/schemas/__init__.py
builtapi/core/schemas/common.py
builtapi/core/schemas/entities.py
builtapi/core/schemas/members.py
builtapi/core/schemas/mongo.py
builtapi/core/schemas/records.py
builtapi/core/schemas/users.py
builtapi/core/schemas/views.py
builtapi/core/schemas/workspaces.py
builtapi/core/validators/__init__.py
builtapi/core/validators/view.py
builtapi/session.py
builtapi/settings.py
builtapi/token.py
builtapi/utils.py
builtapi-0.2.5.dist-info/METADATA
builtapi-0.2.5.dist-info/WHEEL
builtapi-0.2.5.dist-info/RECORD
