Metadata-Version: 2.3
Name: builtapi
Version: 0.2.5
Summary: 
Author: Dreamlone
Author-email: mik_sar@mail.ru
Requires-Python: >=3.10,<4.0
Classifier: Programming Language :: Python :: 3
Classifier: Programming Language :: Python :: 3.10
Classifier: Programming Language :: Python :: 3.11
Classifier: Programming Language :: Python :: 3.12
Classifier: Programming Language :: Python :: 3.13
Requires-Dist: loguru (>=0.7.2,<0.8.0)
Requires-Dist: pydantic (>=2.6.0,<3.0.0)
Requires-Dist: pydantic-core (>=2.20.1,<3.0.0)
Requires-Dist: pytest (>=8.0.0,<9.0.0)
Requires-Dist: requests (>=2.31.0,<3.0.0)
Requires-Dist: requests-mock (>=1.12.1,<2.0.0)
